BayesComBat/__init__.py
BayesComBat/harmonize.py
bayescombat-0.0.7.dist-info/METADATA
bayescombat-0.0.7.dist-info/WHEEL
bayescombat-0.0.7.dist-info/RECORD
